dictionary/__init__.py
dictionary/dictionary.py
CS453_21802539_very_simple_dictionary-2.0.1.dist-info/METADATA
CS453_21802539_very_simple_dictionary-2.0.1.dist-info/WHEEL
CS453_21802539_very_simple_dictionary-2.0.1.dist-info/top_level.txt
CS453_21802539_very_simple_dictionary-2.0.1.dist-info/RECORD
